vttLib/__init__.py
vttLib/__main__.py
vttLib/_version.py
vttLib/parser.py
vttLib/transfer.py
vttLib-0.12.0.dist-info/LICENSE
vttLib-0.12.0.dist-info/METADATA
vttLib-0.12.0.dist-info/WHEEL
vttLib-0.12.0.dist-info/top_level.txt
vttLib-0.12.0.dist-info/RECORD
