Metadata-Version: 2.1
Name: vttLib
Version: 0.12.0
Summary: Compile Visual TrueType assembly with FontTools.
Author-email: Dalton Maag Ltd <info@daltonmaag.com>
License: MIT
Project-URL: Source, https://github.com/daltonmaag/vttLib
Requires-Python: >=3.7
License-File: LICENSE
